django_opt_out/__init__.py
django_opt_out/admin.py
django_opt_out/app_settings.py
django_opt_out/apps.py
django_opt_out/cli.py
django_opt_out/factories.py
django_opt_out/forms.py
django_opt_out/models.py
django_opt_out/resources.py
django_opt_out/signals.py
django_opt_out/urls.py
django_opt_out/utils.py
django_opt_out/views.py
django_opt_out/locales/pl_PL/LC_MESSAGES/django.mo
django_opt_out/locales/pl_PL/LC_MESSAGES/django.po
django_opt_out/management/__init__.py
django_opt_out/management/commands/__init__.py
django_opt_out/management/commands/feedback-translations.csv
django_opt_out/management/commands/feedback.csv
django_opt_out/management/commands/opt_out_feedback_defaults.py
django_opt_out/management/commands/tags.csv
django_opt_out/migrations/0001_initial.py
django_opt_out/migrations/0002_auto_20171214_1726.py
django_opt_out/migrations/0003_auto_20190417_1404.py
django_opt_out/migrations/__init__.py
django_opt_out/plugins/__init__.py
django_opt_out/plugins/sparkpost/__init__.py
django_opt_out/plugins/sparkpost/apps.py
django_opt_out/plugins/sparkpost/hooks.py
django_opt_out/plugins/sparkpost/signals.py
django_opt_out/plugins/sparkpost/urls.py
django_opt_out/plugins/sparkpost/views.py
django_opt_out/static/django_opt_out/css/django_opt_out.css
django_opt_out/static/django_opt_out/img/.gitignore
django_opt_out/static/django_opt_out/js/django_opt_out.js
django_opt_out/templates/django_opt_out/base.html
django_opt_out/templates/django_opt_out/OptOut/form.html
django_opt_out/templates/django_opt_out/OptOut/form_apologies.html
django_opt_out/templates/django_opt_out/OptOut/removed.html
django_opt_out/templates/django_opt_out/OptOut/success.html
django_opt_out/templates/django_opt_out/OptOut/success_apologies.html
django_opt_out-0.9.6.dist-info/AUTHORS.rst
django_opt_out-0.9.6.dist-info/LICENSE
django_opt_out-0.9.6.dist-info/METADATA
django_opt_out-0.9.6.dist-info/WHEEL
django_opt_out-0.9.6.dist-info/entry_points.txt
django_opt_out-0.9.6.dist-info/top_level.txt
django_opt_out-0.9.6.dist-info/RECORD
