Metadata-Version: 2.1
Name: django-opt-out
Version: 0.9.6
Summary: Allow everybody to unsubscribe your messages, user accounts are not required.
Home-page: https://github.com/wooyek/django-opt-out
Author: Janusz Skonieczny
Author-email: js+pypi@bravelabs.pl
License: MIT license
Keywords: django-opt-out
Platform: UNKNOWN
Classifier: Development Status :: 3 - Alpha
Classifier: Framework :: Django :: 1.10
Classifier: Intended Audience :: Developers
Classifier: License :: OSI Approved :: MIT License
Classifier: Natural Language :: English
Classifier: Programming Language :: Python :: 2.7
Classifier: Programming Language :: Python :: 3.5
Requires-Dist: click
Requires-Dist: django-bootstrap-form
Requires-Dist: django-import-export
Requires-Dist: django-pascal-templates
Requires-Dist: django-powerbank
Requires-Dist: markdown
Requires-Dist: django (>=1.11)
Requires-Dist: pathlib ; python_version < "3.3"
Requires-Dist: django (<2.0) ; python_version < "3.4"
Requires-Dist: enum34 ; python_version < "3.4"
Requires-Dist: django (<2.1) ; python_version < "3.5"
Requires-Dist: django ; python_version >= "3.5"
Provides-Extra: factories
Requires-Dist: factory-boy ; extra == 'factories'
Provides-Extra: sparkpost
Requires-Dist: sparkpost (>=1.3.6) ; extra == 'sparkpost'
